HoyoDL/__init__.py
HoyoDL/main.py
HoyoDL-0.1.3.dist-info/LICENSE
HoyoDL-0.1.3.dist-info/METADATA
HoyoDL-0.1.3.dist-info/WHEEL
HoyoDL-0.1.3.dist-info/top_level.txt
HoyoDL-0.1.3.dist-info/RECORD
