Metadata-Version: 2.1
Name: HoyoDL
Version: 0.1.3
Summary: Download any game file at any version of Hoyo games
Home-page: https://github.com/Escartem/HoyoDL
Author: Escartem
Author-email: escartem.github@gmail.com
License: UNKNOWN
Platform: UNKNOWN
Classifier: Programming Language :: Python :: 3
Classifier: License :: Other/Proprietary License
Classifier: Operating System :: OS Independent
Requires-Python: >=3.10
Requires-Dist: requests
